hadrian.py
hadrian_proxy-0.9.0.dist-info/WHEEL
hadrian_proxy-0.9.0.dist-info/METADATA
hadrian_proxy-0.9.0.dist-info/RECORD
